azureml/__init__.py
azureml/webservice_schema/__init__.py
azureml/webservice_schema/_base_util.py
azureml/webservice_schema/_constants.py
azureml/webservice_schema/_numpy_util.py
azureml/webservice_schema/_pandas_util.py
azureml/webservice_schema/_python_util.py
azureml/webservice_schema/_schema_objects.py
azureml/webservice_schema/_schema_util.py
azureml/webservice_schema/_spark_util.py
azureml/webservice_schema/_swagger_from_dtype.py
azureml/webservice_schema/_swagger_from_python.py
azureml/webservice_schema/_swagger_from_spark.py
azureml/webservice_schema/_utilities.py
azureml/webservice_schema/_version.py
azureml/webservice_schema/data_types.py
azureml/webservice_schema/sample_definition.py
azureml/webservice_schema/schema_generation.py
azureml/webservice_schema/schema_exceptions/__init__.py
azureml/webservice_schema/schema_exceptions/api_exception.py
azureml/webservice_schema/schema_exceptions/client_side_exception.py
azureml/webservice_schema/schema_exceptions/server_side_exception.py
azureml_webservice_schema-1.0.33.dist-info/DESCRIPTION.rst
azureml_webservice_schema-1.0.33.dist-info/LICENSE.txt
azureml_webservice_schema-1.0.33.dist-info/METADATA
azureml_webservice_schema-1.0.33.dist-info/RECORD
azureml_webservice_schema-1.0.33.dist-info/WHEEL
azureml_webservice_schema-1.0.33.dist-info/metadata.json
azureml_webservice_schema-1.0.33.dist-info/top_level.txt
