Metadata-Version: 2.0
Name: azureml-webservice-schema
Version: 1.0.33
Summary: azureml webservice schema
Home-page: https://docs.microsoft.com/en-us/azure/machine-learning/service/
Author: Microsoft Corp
License: https://aka.ms/azureml-sdk-license
Platform: UNKNOWN
Classifier: Development Status :: 4 - Beta
Classifier: Framework :: IPython
Classifier: Intended Audience :: Developers
Classifier: Intended Audience :: Science/Research
Classifier: Topic :: Multimedia :: Graphics
Classifier: Programming Language :: Python :: 3
Classifier: Programming Language :: Python :: 3.3
Classifier: Programming Language :: Python :: 3.4
Classifier: Programming Language :: Python :: 3.5
Requires-Dist: requests (>=2.17.3)
Requires-Dist: six (>=1.10)
Requires-Dist: adal (>=0.4.5)
Requires-Dist: python-dateutil (>=2.5.3)
Requires-Dist: pytz (>=2017.2)
Requires-Dist: liac-arff (>=2.1.1)
Requires-Dist: numpy (>=1.13.0)
Requires-Dist: pandas (>=0.20.2)
Requires-Dist: dill (>=0.2.7.1)
Requires-Dist: pyspark (==2.3.1)
